wrapup/__init__.py
wrapup/checker.py
wrapup/filepath.py
wrapup/helpers.py
wrapup/master.py
wrapup/python_file_error.py
wrapup/workers.py
wrapup-1.0.1.dist-info/LICENSE.txt
wrapup-1.0.1.dist-info/METADATA
wrapup-1.0.1.dist-info/WHEEL
wrapup-1.0.1.dist-info/top_level.txt
wrapup-1.0.1.dist-info/RECORD
