Metadata-Version: 2.1
Name: wrapup
Version: 1.0.1
Summary: A library that is used to remove print statements or converting quotes in python files (if present) in a folder
Home-page: UNKNOWN
Author: Faizan Mombasawala
Author-email: mombasawalafaizan6@gmail.com
License: UNKNOWN
Keywords: library,format,remove prints,print,
Platform: UNKNOWN
Classifier: Programming Language :: Python :: 3
Classifier: Programming Language :: Python :: 3.6
Classifier: Programming Language :: Python :: 3.7
Classifier: Programming Language :: Python :: 3.8
Classifier: Programming Language :: Python :: 3.9
Classifier: Programming Language :: Python :: 3 :: Only
Classifier: Operating System :: OS Independent
Requires-Python: >=3.6, <4
License-File: LICENSE.txt
